botoinator/__init__.py
botoinator/session.py
botoinator-0.0.6.dist-info/LICENSE
botoinator-0.0.6.dist-info/METADATA
botoinator-0.0.6.dist-info/WHEEL
botoinator-0.0.6.dist-info/top_level.txt
botoinator-0.0.6.dist-info/RECORD
