Metadata-Version: 2.1
Name: botoinator
Version: 0.0.6
Summary: A decoration mechanism for boto3 that allows automatic decoration of any and all boto3 clients and resources
Home-page: https://github.com/QuiNovas/botoinator
Author: Joseph Wortmann
Author-email: jwortmann@quinovas.com
License: Apache 2.0
Platform: UNKNOWN
Classifier: Development Status :: 4 - Beta
Classifier: Intended Audience :: Developers
Classifier: License :: OSI Approved :: Apache Software License
Classifier: Programming Language :: Python :: 3.7
Provides-Extra: boto3
Requires-Dist: boto3 ; extra == 'boto3'
